congablobservice/__init__.py
congablobservice/blob_service.py
congablobservice-0.0.2.dist-info/LICENSE
congablobservice-0.0.2.dist-info/METADATA
congablobservice-0.0.2.dist-info/WHEEL
congablobservice-0.0.2.dist-info/top_level.txt
congablobservice-0.0.2.dist-info/RECORD
