Metadata-Version: 2.1
Name: congablobservice
Version: 0.0.2
Summary: A package defines methods for Azure Blob Storage access
Home-page: https://github.com/nmarkovic-conga/conga-worker-service/
Author: Nikola Markovic
Author-email: nmarkovic@conga.com
License: UNKNOWN
Platform: UNKNOWN
Classifier: Programming Language :: Python :: 3.9
Classifier: License :: OSI Approved :: GNU General Public License v3 (GPLv3)
License-File: LICENSE
Requires-Dist: pip (>=21.2.4)
Requires-Dist: wheel (>=0.37.0)
Requires-Dist: azure.storage.blob (>=1.2.0)
